.bandit
.editorconfig
.gitignore
.gitlab-ci.yml
.mailmap
.safety-policy.yml
.weblate
.yamllint
CHANGELOG.md
CONTRIBUTING.md
LICENSE
MANIFEST.in
README.md
fdroid
gradlew-fdroid
jenkins-build-all
jenkins-setup-build-environment
jenkins-test
makebuildserver
pyproject.toml
setup.cfg
setup.py
.vscode/extensions.json
.vscode/settings.json
.well-known/funding-manifest-urls
buildserver/.gitignore
buildserver/Dockerfile
buildserver/Vagrantfile
buildserver/config.buildserver.yml
buildserver/provision-android-ndk
buildserver/provision-android-sdk
buildserver/provision-apt-get-install
buildserver/provision-apt-proxy
buildserver/provision-buildserverid
buildserver/provision-disable-analytics
buildserver/provision-gradle
buildserver/setup-env-vars
completion/bash-completion
docs/Makefile
docs/make.bat
docs/source/conf.py
docs/source/index.rst
examples/Vagrantfile.yaml
examples/config.yml
examples/fdroid_clean_repos.py
examples/fdroid_export_keystore_to_nitrokey.py
examples/fdroid_exportkeystore.py
examples/fdroid_extract_repo_pubkey.py
examples/fdroid_fetchsrclibs.py
examples/fdroid_nitrokeyimport.py
examples/opensc-fdroid.cfg
examples/public-read-only-s3-bucket-policy.json
examples/template.yml
fdroidserver/__init__.py
fdroidserver/__main__.py
fdroidserver/_yaml.py
fdroidserver/apksigcopier.py
fdroidserver/btlog.py
fdroidserver/build.py
fdroidserver/checkupdates.py
fdroidserver/common.py
fdroidserver/deploy.py
fdroidserver/exception.py
fdroidserver/github.py
fdroidserver/gpgsign.py
fdroidserver/import_subcommand.py
fdroidserver/index.py
fdroidserver/init.py
fdroidserver/install.py
fdroidserver/lint.py
fdroidserver/looseversion.py
fdroidserver/metadata.py
fdroidserver/mirror.py
fdroidserver/net.py
fdroidserver/nightly.py
fdroidserver/publish.py
fdroidserver/readmeta.py
fdroidserver/rewritemeta.py
fdroidserver/scanner.py
fdroidserver/signatures.py
fdroidserver/signindex.py
fdroidserver/tail.py
fdroidserver/update.py
fdroidserver/verify.py
fdroidserver/vmtools.py
fdroidserver.egg-info/PKG-INFO
fdroidserver.egg-info/SOURCES.txt
fdroidserver.egg-info/dependency_links.txt
fdroidserver.egg-info/entry_points.txt
fdroidserver.egg-info/requires.txt
fdroidserver.egg-info/top_level.txt
